setup.py
gcs_oauth2_boto_plugin/__init__.py
gcs_oauth2_boto_plugin/oauth2_client.py
gcs_oauth2_boto_plugin/oauth2_helper.py
gcs_oauth2_boto_plugin/oauth2_plugin.py
gcs_oauth2_boto_plugin/test_oauth2_client.py
gcs_oauth2_boto_plugin_grow.egg-info/PKG-INFO
gcs_oauth2_boto_plugin_grow.egg-info/SOURCES.txt
gcs_oauth2_boto_plugin_grow.egg-info/dependency_links.txt
gcs_oauth2_boto_plugin_grow.egg-info/requires.txt
gcs_oauth2_boto_plugin_grow.egg-info/top_level.txt
gcs_oauth2_boto_plugin_grow.egg-info/zip-safe