Metadata-Version: 1.1
Name: gcs-oauth2-boto-plugin-grow
Version: 1.14
Summary: Auth plugin allowing use the use of OAuth 2.0 credentials for Google Cloud Storage in the Boto library.
Home-page: https://developers.google.com/storage/docs/gspythonlibrary
Author: Google Inc.
Author-email: gs-team@google.com
License: Apache 2.0
Download-URL: https://github.com/grow/gcs-oauth2-boto-plugin
Platform: any
